ncdata/__init__.py
ncdata/_core.py
ncdata/_version.py
ncdata/dataset_like.py
ncdata/iris.py
ncdata/iris_xarray.py
ncdata/netcdf4.py
ncdata/threadlock_sharing.py
ncdata/xarray.py
ncdata/utils/__init__.py
ncdata/utils/_compare_nc_datasets.py
ncdata/utils/_copy.py
ncdata/utils/_dim_indexing.py
ncdata/utils/_rename_dim.py
ncdata/utils/_save_errors.py
ncdata-0.3.1.dist-info/licenses/LICENSE
ncdata-0.3.1.dist-info/METADATA
ncdata-0.3.1.dist-info/WHEEL
ncdata-0.3.1.dist-info/top_level.txt
ncdata-0.3.1.dist-info/RECORD
