Metadata-Version: 2.4
Name: ncdata
Version: 0.3.1
Summary: Abstract NetCDF data objects, providing fast data transfer between analysis packages.
Author-email: Patrick Peglar <patrick.peglar@metoffice.gov.uk>
License: BSD-3-Clause
Project-URL: Code, https://github.com/pp-mo/ncdata
Project-URL: Discussions, https://github.com/pp-mo/ncdata/discussions
Project-URL: Documentation, https://ncdata.readthedocs.io
Project-URL: Issues, https://github.com/pp-mo/ncdata/issues
Keywords: cf-metadata,data-analysis,netcdf,iris,xarray
Classifier: Development Status :: 4 - Beta
Classifier: Intended Audience :: Science/Research
Classifier: License :: OSI Approved :: BSD License
Classifier: Natural Language :: English
Classifier: Operating System :: POSIX
Classifier: Operating System :: POSIX :: Linux
Classifier: Operating System :: Unix
Classifier: Programming Language :: Python
Classifier: Programming Language :: Python :: 3 :: Only
Classifier: Programming Language :: Python :: 3.7
Classifier: Programming Language :: Python :: 3.8
Classifier: Programming Language :: Python :: 3.9
Classifier: Programming Language :: Python :: 3.10
Classifier: Programming Language :: Python :: 3.11
Classifier: Programming Language :: Python :: 3.12
Classifier: Programming Language :: Python :: 3.13
Classifier: Topic :: Scientific/Engineering
Requires-Python: <3.14,>=3.7
License-File: LICENSE
Requires-Dist: numpy
Requires-Dist: dask
Requires-Dist: netCDF4
Dynamic: license-file
